basetoascii/__init__.py
basetoascii/ascii_from_base.py
basetoascii/ascii_from_hex.py
basetoascii/convertbase.py
basetoascii/convertbase.py.py
ninehundred_basetoascii-0.0.11.dist-info/METADATA
ninehundred_basetoascii-0.0.11.dist-info/WHEEL
ninehundred_basetoascii-0.0.11.dist-info/entry_points.txt
ninehundred_basetoascii-0.0.11.dist-info/top_level.txt
ninehundred_basetoascii-0.0.11.dist-info/RECORD
