Metadata-Version: 2.1
Name: ninehundred-basetoascii
Version: 0.0.11
Summary: Converts input from binary, hex, or oct to readable text
Home-page: https://github.com/ninehundred/basetoascii
Author: Daniel O'Dowd
Author-email: ninehundred@hotmail.co.uk
License: MIT
Platform: UNKNOWN
Classifier: License :: OSI Approved :: MIT License
Classifier: Programming Language :: Python :: 3
Classifier: Programming Language :: Python :: 3.7
